uv_test/__init__.py
uv_test/uv_test.py
ain_uv_test-0.1.0.dist-info/METADATA
ain_uv_test-0.1.0.dist-info/WHEEL
ain_uv_test-0.1.0.dist-info/top_level.txt
ain_uv_test-0.1.0.dist-info/RECORD
