Metadata-Version: 2.4
Name: ain-uv-test
Version: 0.1.0
Summary: Add your description here
Requires-Python: >=3.11
Requires-Dist: numpy>=2.3.2
